dem_entropy/__init__.py
dem_entropy/clem.py
dem_entropy-0.0.4.dist-info/DESCRIPTION.rst
dem_entropy-0.0.4.dist-info/METADATA
dem_entropy-0.0.4.dist-info/RECORD
dem_entropy-0.0.4.dist-info/WHEEL
dem_entropy-0.0.4.dist-info/entry_points.txt
dem_entropy-0.0.4.dist-info/metadata.json
dem_entropy-0.0.4.dist-info/top_level.txt
